{
  "data_relatorio": "13/07/2026",
  "gerado_em": "2026-07-13T16:00:07",
  "atualizado_em": "2026-07-13T19:05:24",
  "totais": {
    "prog": 52,
    "carr": 34,
    "falta": 18,
    "tn_prev": 1725.38,
    "tn_carr": 1093.33
  },
  "por_cliente": [
    {
      "cliente": "ITAMBÉ",
      "prog": 17,
      "carr": 9,
      "falta": 8,
      "tn_prev": 625.69,
      "tn_carr": 322.69
    },
    {
      "cliente": "BRASKEM",
      "prog": 9,
      "carr": 9,
      "falta": 0,
      "tn_prev": 307.0,
      "tn_carr": 335.69
    },
    {
      "cliente": "GABRIELLA",
      "prog": 8,
      "carr": 8,
      "falta": 0,
      "tn_prev": 200.0,
      "tn_carr": 222.85
    },
    {
      "cliente": "CIM. LIZ",
      "prog": 4,
      "carr": 1,
      "falta": 3,
      "tn_prev": 159.63,
      "tn_carr": 35.63
    },
    {
      "cliente": "BELLUNO",
      "prog": 4,
      "carr": 4,
      "falta": 0,
      "tn_prev": 120.0,
      "tn_carr": 122.62
    },
    {
      "cliente": "PETRORECONCAVO",
      "prog": 2,
      "carr": 0,
      "falta": 2,
      "tn_prev": 100.0,
      "tn_carr": 0.0
    },
    {
      "cliente": "METROPOLITANA",
      "prog": 2,
      "carr": 0,
      "falta": 2,
      "tn_prev": 68.0,
      "tn_carr": 0.0
    },
    {
      "cliente": "RIO DESERTO",
      "prog": 2,
      "carr": 1,
      "falta": 1,
      "tn_prev": 62.0,
      "tn_carr": 30.79
    },
    {
      "cliente": "APERAM",
      "prog": 2,
      "carr": 0,
      "falta": 2,
      "tn_prev": 60.0,
      "tn_carr": 0.0
    },
    {
      "cliente": "COMERCIAL CARVALHO",
      "prog": 2,
      "carr": 2,
      "falta": 0,
      "tn_prev": 23.06,
      "tn_carr": 23.06
    }
  ],
  "por_produto": [
    {
      "produto": "TÉRMICO",
      "prog": 25,
      "carr": 22,
      "falta": 3,
      "tn_prev": 757.0,
      "tn_carr": 711.95
    },
    {
      "produto": "GESSO",
      "prog": 17,
      "carr": 9,
      "falta": 8,
      "tn_prev": 625.69,
      "tn_carr": 322.69
    },
    {
      "produto": "CARVÃO",
      "prog": 4,
      "carr": 1,
      "falta": 3,
      "tn_prev": 159.63,
      "tn_carr": 35.63
    },
    {
      "produto": "PETRÓLEO",
      "prog": 2,
      "carr": 0,
      "falta": 2,
      "tn_prev": 100.0,
      "tn_carr": 0.0
    },
    {
      "produto": "COQUE",
      "prog": 2,
      "carr": 0,
      "falta": 2,
      "tn_prev": 60.0,
      "tn_carr": 0.0
    },
    {
      "produto": "Carregamento Sucata",
      "prog": 2,
      "carr": 2,
      "falta": 0,
      "tn_prev": 23.06,
      "tn_carr": 23.06
    }
  ],
  "lotes": [
    {
      "lote": "ITAMBÉ - GESSO - MAGIC CELESTE - PILHA 19",
      "cliente": "ITAMBÉ",
      "produto": "GESSO",
      "prog": 17,
      "carr": 9,
      "falta": 8,
      "tn_prev": 625.69,
      "tn_carr": 322.69,
      "transportadoras": [
        {
          "nome": "TRANSP. BONTORIN (SC)",
          "cnpj": "81429755000299",
          "prog": 1,
          "carr": 0,
          "falta": 1,
          "tn_prev": 49.0,
          "tn_carr": 0.0
        },
        {
          "nome": "PAULISTA TRANSP. (SC)",
          "cnpj": "80776784000264",
          "prog": 6,
          "carr": 2,
          "falta": 4,
          "tn_prev": 219.64,
          "tn_carr": 73.64
        },
        {
          "nome": "H.R. TRANSP. (SC)",
          "cnpj": "79838694000190",
          "prog": 10,
          "carr": 7,
          "falta": 3,
          "tn_prev": 357.05,
          "tn_carr": 249.05
        }
      ]
    },
    {
      "lote": "BRASKEM - TÉRMICO JOKER - PILHA 92",
      "cliente": "BRASKEM",
      "produto": "TÉRMICO",
      "prog": 9,
      "carr": 9,
      "falta": 0,
      "tn_prev": 307.0,
      "tn_carr": 335.69,
      "transportadoras": [
        {
          "nome": "ROTA 101 (SC)",
          "cnpj": "21269148000287",
          "prog": 2,
          "carr": 2,
          "falta": 0,
          "tn_prev": 65.0,
          "tn_carr": 71.36
        },
        {
          "nome": "LUAN DE SOUZA BONFANTE (SC)",
          "cnpj": "21430615000128",
          "prog": 1,
          "carr": 1,
          "falta": 0,
          "tn_prev": 37.0,
          "tn_carr": 38.77
        },
        {
          "nome": "FRATELLI (SC)",
          "cnpj": "10989401000170",
          "prog": 3,
          "carr": 3,
          "falta": 0,
          "tn_prev": 131.0,
          "tn_carr": 133.47
        },
        {
          "nome": "CANEVER (SC)",
          "cnpj": "42029409000180",
          "prog": 3,
          "carr": 3,
          "falta": 0,
          "tn_prev": 74.0,
          "tn_carr": 92.09
        }
      ]
    },
    {
      "lote": "GABRIELLA - TÉRMICO JOKER - PILHA 92",
      "cliente": "GABRIELLA",
      "produto": "TÉRMICO",
      "prog": 8,
      "carr": 8,
      "falta": 0,
      "tn_prev": 200.0,
      "tn_carr": 222.85,
      "transportadoras": [
        {
          "nome": "GABRIELLA MINERACAO (SC)",
          "cnpj": "07105967000187",
          "prog": 8,
          "carr": 8,
          "falta": 0,
          "tn_prev": 200.0,
          "tn_carr": 222.85
        }
      ]
    },
    {
      "lote": "CIM. LIZ - CARVÃO - FENG ZE HAI - PILHA 47",
      "cliente": "CIM. LIZ",
      "produto": "CARVÃO",
      "prog": 4,
      "carr": 1,
      "falta": 3,
      "tn_prev": 159.63,
      "tn_carr": 35.63,
      "transportadoras": [
        {
          "nome": "RODOSAFRA (RJ)",
          "cnpj": "26549889000669",
          "prog": 1,
          "carr": 0,
          "falta": 1,
          "tn_prev": 48.0,
          "tn_carr": 0.0
        },
        {
          "nome": "EXP. TS (RJ)",
          "cnpj": "05324485000516",
          "prog": 1,
          "carr": 1,
          "falta": 0,
          "tn_prev": 35.63,
          "tn_carr": 35.63
        },
        {
          "nome": "DC4 TRANSP. (RJ)",
          "cnpj": "41539746000317",
          "prog": 2,
          "carr": 0,
          "falta": 2,
          "tn_prev": 76.0,
          "tn_carr": 0.0
        }
      ]
    },
    {
      "lote": "BELLUNO - TÉRMICO JOKER - PILHA 92",
      "cliente": "BELLUNO",
      "produto": "TÉRMICO",
      "prog": 4,
      "carr": 4,
      "falta": 0,
      "tn_prev": 120.0,
      "tn_carr": 122.62,
      "transportadoras": [
        {
          "nome": "BELLUNO (SC)",
          "cnpj": "83163576000105",
          "prog": 4,
          "carr": 4,
          "falta": 0,
          "tn_prev": 120.0,
          "tn_carr": 122.62
        }
      ]
    },
    {
      "lote": "PETRORECONCAVO - PETROLEO - GUAMARE",
      "cliente": "PETRORECONCAVO",
      "produto": "PETRÓLEO",
      "prog": 2,
      "carr": 0,
      "falta": 2,
      "tn_prev": 100.0,
      "tn_carr": 0.0,
      "transportadoras": [
        {
          "nome": "MINAS TRADING (RN)",
          "cnpj": "05456420001091",
          "prog": 2,
          "carr": 0,
          "falta": 2,
          "tn_prev": 100.0,
          "tn_carr": 0.0
        }
      ]
    },
    {
      "lote": "METROPOLITANA - TÉRMICO JOKER - PILHA 92",
      "cliente": "METROPOLITANA",
      "produto": "TÉRMICO",
      "prog": 2,
      "carr": 0,
      "falta": 2,
      "tn_prev": 68.0,
      "tn_carr": 0.0,
      "transportadoras": [
        {
          "nome": "PAGANI (SC)",
          "cnpj": "26291836000186",
          "prog": 2,
          "carr": 0,
          "falta": 2,
          "tn_prev": 68.0,
          "tn_carr": 0.0
        }
      ]
    },
    {
      "lote": "RIO DESERTO - TÉRMICO JOKER - PILHA 92",
      "cliente": "RIO DESERTO",
      "produto": "TÉRMICO",
      "prog": 2,
      "carr": 1,
      "falta": 1,
      "tn_prev": 62.0,
      "tn_carr": 30.79,
      "transportadoras": [
        {
          "nome": "PAGANI (SC)",
          "cnpj": "26291836000186",
          "prog": 2,
          "carr": 1,
          "falta": 1,
          "tn_prev": 62.0,
          "tn_carr": 30.79
        }
      ]
    },
    {
      "lote": "APERAM- COQUE - PILHA 80 - MAIO",
      "cliente": "APERAM",
      "produto": "COQUE",
      "prog": 2,
      "carr": 0,
      "falta": 2,
      "tn_prev": 60.0,
      "tn_carr": 0.0,
      "transportadoras": [
        {
          "nome": "SAMATRA (MG)",
          "cnpj": "20752507000370",
          "prog": 2,
          "carr": 0,
          "falta": 2,
          "tn_prev": 60.0,
          "tn_carr": 0.0
        }
      ]
    },
    {
      "lote": "COMERCIAL CARVALHO - CARREGAMENTO SUCATA - PILHA 75",
      "cliente": "COMERCIAL CARVALHO",
      "produto": "Carregamento Sucata",
      "prog": 2,
      "carr": 2,
      "falta": 0,
      "tn_prev": 23.06,
      "tn_carr": 23.06,
      "transportadoras": [
        {
          "nome": "COMERCIAL CARVALHO",
          "cnpj": "05362003000199",
          "prog": 2,
          "carr": 2,
          "falta": 0,
          "tn_prev": 23.06,
          "tn_carr": 23.06
        }
      ]
    }
  ]
}